README
setup.py
bambu_mapping/__init__.py
bambu_mapping/urls.py
bambu_mapping/views.py
bambu_mapping.egg-info/PKG-INFO
bambu_mapping.egg-info/SOURCES.txt
bambu_mapping.egg-info/dependency_links.txt
bambu_mapping.egg-info/requires.txt
bambu_mapping.egg-info/top_level.txt
bambu_mapping/providers/__init__.py
bambu_mapping/providers/base.py
bambu_mapping/providers/google.py
bambu_mapping/providers/osm.py
bambu_mapping/templates/mapping/bambu.mapping.js
bambu_mapping/templatetags/__init__.py
bambu_mapping/templatetags/mapping.py