Metadata-Version: 1.1
Name: bambu-mapping
Version: 2.0
Summary: A pluggable, provider-based system for rendering maps
Home-page: https://github.com/iamsteadman/bambu-mapping
Author: Steadman
Author-email: mark@steadman.io
License: UNKNOWN
Platform: UNKNOWN
Classifier: Development Status :: 4 - Beta
Classifier: Environment :: Web Environment
Classifier: Framework :: Django
